tizori_cli/commands/__init__.py
tizori_cli/commands/applications.py
tizori_cli/commands/auth.py
tizori_cli/commands/base.py
tizori_cli/commands/roles.py
tizori_cli/commands/users.py
tizori_cli/config.py
tizori_cli/main.py
tizori_cli/wrapper/__init__.py
tizori_cli/wrapper/applications.py
tizori_cli/wrapper/auth.py
tizori_cli/wrapper/base.py
tizori_cli/wrapper/roles.py
tizori_cli/wrapper/users.py
tizori_cli-0.1.1.dist-info/LICENSE
tizori_cli-0.1.1.dist-info/METADATA
tizori_cli-0.1.1.dist-info/WHEEL
tizori_cli-0.1.1.dist-info/entry_points.txt
tizori_cli-0.1.1.dist-info/RECORD
