Metadata-Version: 2.1
Name: tizori-cli
Version: 0.1.1
Summary: 
Author: Dhruv Shah
Author-email: dhruvshahrds@gmail.com
Requires-Python: >=3.12,<4.0
Classifier: Programming Language :: Python :: 3
Classifier: Programming Language :: Python :: 3.12
Requires-Dist: pyyaml (>=6.0.1,<7.0.0)
Requires-Dist: requests (>=2.32.3,<3.0.0)
Requires-Dist: typer[all] (>=0.12.3,<0.13.0)
